{"announcements_qq-group-closed.md":"VrY9Qq5n","announcements_index.md":"CloOK-HR","blog_202309.md":"DXlhRCS4","blog_20240101.md":"Cb5ozNm6","docs_pages.md":"BDxntyEO","blog_20240116.md":"Du23Thhv","blog_202402.md":"DrEgVi0C","announcements_observation-period-abolished.md":"7i812Yz9","blog_202310.md":"C04_UpRo","blog_202307.md":"CSInk5iM","announcements_regulations.md":"X7fQ2TtE","blog_202212.md":"5gr7j-LX","blog_index.md":"xWB9WkNP","announcements_removed-dead-site.md":"CuumbAm-","index.md":"CL2GiX7P","docs_toyou.md":"-Goi3ZPR","docs_thanks.md":"BmPJ-zvn","docs_qa.md":"D21eZ2GN","blog_202306.md":"CijSpNBG","preference.md":"BaWd02_G","blog_202003.md":"BTzofL7e","announcements_icp-closed.md":"BFMz_98J","docs_join.md":"MVYfCQlw","readme.md":"viaVbqWD","blog_202308.md":"BTMjECc9","docs_intro.md":"C86k5krW"}
