{"announcements_icp-closed.md":"BXOFSD6n","announcements_2025-newyear-activity.md":"D289-IWo","en_us_blog_202306.md":"Dm5P0eNt","en_us_blog_202310.md":"4dkcenDx","blog_202405.md":"9TZVEvLM","en_us_blog_202405.md":"BzchHKL3","docs_index.md":"BWodLrDs","blog_index.md":"Czy2i8ab","blog_202307.md":"CMR3IzsP","blog_20240116.md":"CTFVqjPE","en_us_blog_202309.md":"BvnCmHzA","zh_tw_announcements_qq-group-closed.md":"CZRFHREc","blog_20240101.md":"dk7JnrPU","zh_tw_announcements_icp-closed.md":"BFTO6LcD","zh_tw_blog_202408.md":"BOShklHM","zh_tw_blog_202003.md":"BBOKPRrY","docs_qa.md":"7O4Vvr06","docs_thanks.md":"B0Kht83X","announcements_index.md":"XCLExSK0","announcements_new-regulations.md":"BhqQuMpZ","announcements_observation-period-abolished.md":"CS7r9out","blog_202412.md":"DPjFv2jq","readme.md":"BruI_dHn","blog_202404.md":"CTjXSGNS","en_us_blog_202307.md":"Db4Mb3Ot","en_us_announcements_new-regulations.md":"CFMvXNgk","announcements_regulations.md":"DJzpx3Xa","en_us_blog_202408.md":"ChjYpMi3","en_us_blog_20240116.md":"C_PIzxG4","en_us_blog_202412.md":"B-plY3Yt","announcements_qq-group-closed.md":"HgMhQMLf","en_us_announcements_index.md":"ySoOn4bG","en_us_blog_202003.md":"BWRE0rdE","en_us_docs_join.md":"DOG4Dk8p","en_us_docs_pages.md":"DKEf4HXI","en_us_readme.md":"gnjM-SNj","en_us_blog_202402.md":"DFoqGNa2","docs_pages.md":"C-GABV4M","en_us_blog_202308.md":"DeeSlsf1","en_us_docs_index.md":"DdW2Y56-","en_us_blog_index.md":"BHcT9wQD","blog_202309.md":"CxTW5xxT","zh_tw_blog_20240101.md":"De8bacFR","zh_tw_readme.md":"C1oISEa7","zh_tw_blog_202402.md":"CKKDQOh5","zh_tw_blog_202405.md":"sD9W7iYl","zh_tw_blog_index.md":"CMcUeVZY","zh_tw_blog_202310.md":"DqNHHTLq","zh_tw_blog_202412.md":"CFh4ArnG","zh_tw_docs_index.md":"bD76kyf9","blog_202408.md":"D6FCqaxQ","zh_tw_docs_pages.md":"DM92s_YT","zh_tw_docs_join.md":"CYAu-SEB","zh_tw_docs_qa.md":"DKN6UTL1","zh_tw_docs_thanks.md":"DRpxojZG","zh_tw_index.md":"ncP5GelV","zh_tw_docs_toyou.md":"BHY0pWiI","en_us_announcements_regulations.md":"wY1l6P1E","blog_202402.md":"Czvmpcm0","en_us_docs_thanks.md":"RmsE3vFx","en_us_index.md":"sGNkz49y","index.md":"AKqYlvWF","preference.md":"B5kqB5Yh","zh_tw_announcements_regulations.md":"DZAMmCGS","zh_tw_announcements_2025-newyear-activity.md":"Dnud0xyQ","en_us_docs_toyou.md":"CIGA0i_L","zh_tw_blog_202306.md":"Dn-VZ4hw","zh_tw_blog_202307.md":"BDoyqTh_","blog_202003.md":"ClVhYpm5","blog_202306.md":"CUL42qGU","blog_202310.md":"zGt1alpC","announcements_removed-dead-site.md":"DTgcEHPP","docs_join.md":"C9UV2JEr","zh_tw_announcements_observation-period-abolished.md":"CJ1cS-2T","zh_tw_announcements_index.md":"DdK9guow","blog_202308.md":"Cz6ODvFK","en_us_blog_202212.md":"CVXymtTS","zh_tw_announcements_new-regulations.md":"1qJutDeE","en_us_announcements_2025-newyear-activity.md":"D4UxkqBv","en_us_announcements_qq-group-closed.md":"TDWAv1Id","en_us_announcements_observation-period-abolished.md":"B9wZvmwG","en_us_announcements_icp-closed.md":"Dro2xSqm","en_us_announcements_removed-dead-site.md":"LClUYq_7","en_us_blog_20240101.md":"mKhxYd7h","zh_tw_blog_20240116.md":"D2PIK8Dt","en_us_docs_qa.md":"wmqUy-W7","docs_toyou.md":"CujVNB21","zh_tw_blog_202308.md":"D3y6ksU5","zh_tw_blog_202309.md":"CP0VEpDR","zh_tw_announcements_removed-dead-site.md":"DqCS2ApW","blog_202212.md":"D5PuWlkP","zh_tw_blog_202212.md":"DTqoAntl"}
