{"announcements_observation-period-abolished.md":"BYN2z2f_","blog_202402.md":"DAwGT_La","docs_pages.md":"SisCXe3K","announcements_index.md":"Dk0kMzXv","blog_202212.md":"CbMKh-Lf","announcements_icp-closed.md":"ASiVXSuQ","announcements_regulations.md":"Oxe89Itq","blog_202310.md":"CzuIzIdk","en_us_docs_toyou.md":"Cl_euW9y","docs_qa.md":"B5Hhs76P","docs_intro.md":"fwE-4beH","en_us_blog_202310.md":"DvgpMIFj","en_us_announcements_qq-group-closed.md":"BgZZlP6K","en_us_announcements_removed-dead-site.md":"CcWq2m09","en_us_announcements_icp-closed.md":"BfNm1qYU","en_us_blog_202306.md":"BWDBtIzF","en_us_blog_202003.md":"BR5jGVb_","readme.md":"Bfr0RGqf","en_us_blog_202307.md":"C3RDQT3t","en_us_blog_202308.md":"jJfI5Wl_","blog_202306.md":"DAsvEyUb","blog_202307.md":"miRzmKk2","blog_202308.md":"Ci8bFhL5","docs_thanks.md":"CdWhEzib","docs_toyou.md":"DNaZGNu6","en_us_readme.md":"CjqMQ8B2","announcements_removed-dead-site.md":"44Q325Qw","blog_20240101.md":"v_lMV8Zc","en_us_blog_20240116.md":"BNm-PJWR","blog_20240116.md":"DNb2lGmM","en_us_blog_202402.md":"Cf2pgXIf","en_us_blog_index.md":"ax_d_1SH","zh_hk_blog_202212.md":"v-mUM9iG","en_us_index.md":"BXebFNQU","en_us_docs_intro.md":"CvPRxcgm","en_us_docs_pages.md":"BAQhWmih","en_us_docs_join.md":"B7ulmXsE","zh_tw_blog_202307.md":"Dc38iD77","zh_hk_blog_202308.md":"dinqtiBW","zh_hk_index.md":"BgT2ajb3","zh_tw_readme.md":"ChBWW2JT","zh_tw_announcements_icp-closed.md":"CGTJa2NR","docs_join.md":"BK2THeSJ","en_us_announcements_observation-period-abolished.md":"CqG2El5w","zh_tw_announcements_observation-period-abolished.md":"v8M2Re2Q","zh_tw_announcements_qq-group-closed.md":"qr0zMMCD","en_us_docs_thanks.md":"BxnVQzj0","zh_hk_blog_202306.md":"DNHA9dbJ","zh_hk_blog_202307.md":"BQy18t63","zh_tw_announcements_removed-dead-site.md":"DOpLOoAu","zh_tw_blog_202309.md":"Zq2mPm0j","zh_tw_blog_202003.md":"BipuhI6S","zh_tw_blog_20240101.md":"D8cc367U","zh_tw_blog_202212.md":"CbTKZVsv","en_us_docs_qa.md":"DegvPGml","zh_tw_announcements_index.md":"DRACEwip","zh_tw_blog_20240116.md":"CLyeNBta","blog_202309.md":"ZzJfsYU6","zh_tw_blog_202402.md":"CXlM-Nad","zh_tw_blog_index.md":"DZJh3ye3","zh_tw_announcements_regulations.md":"uNOXIUMH","zh_tw_docs_join.md":"CWYJ4WZ0","zh_tw_docs_pages.md":"Crn7urKr","zh_tw_blog_202306.md":"BmP14E0j","zh_tw_docs_qa.md":"CxLXw3hb","preference.md":"K_nOgoFb","zh_tw_docs_thanks.md":"BscZBWBg","blog_202003.md":"Crz4Gr74","zh_tw_docs_toyou.md":"CAjI0MiR","zh_tw_index.md":"Bc9ew2yz","zh_hk_announcements_removed-dead-site.md":"BQrG8pn0","zh_hk_readme.md":"DMbN_ebE","en_us_blog_202212.md":"DL-3f8Tc","zh_hk_announcements_index.md":"ClIxR5Bx","zh_tw_blog_202308.md":"CZVLGHpn","zh_hk_announcements_observation-period-abolished.md":"Z5Qed3vG","index.md":"jJi7SS9b","zh_hk_docs_intro.md":"CVRFxJ_d","blog_index.md":"Rif_JYP8","zh_hk_announcements_regulations.md":"DTVYR8-T","en_us_announcements_index.md":"C0LBFS5S","zh_hk_docs_qa.md":"BsAZis7f","zh_hk_announcements_icp-closed.md":"Cn-R_YOa","en_us_blog_20240101.md":"lI3tM0dI","announcements_qq-group-closed.md":"BtJz2Nxm","zh_hk_blog_202309.md":"CSn82rG4","en_us_announcements_regulations.md":"DCegPtYI","zh_hk_blog_202003.md":"OhN2RZI6","zh_hk_announcements_qq-group-closed.md":"Bskrw16E","en_us_blog_202309.md":"7AG5Ve9r","zh_hk_blog_index.md":"CrGjGx68","zh_tw_docs_intro.md":"DG8MSk-m","zh_hk_blog_202310.md":"gEGC-hR5","zh_hk_blog_20240101.md":"Dak6jhKm","zh_hk_blog_20240116.md":"dep8RvOt","zh_hk_blog_202402.md":"DNs1GmpF","zh_tw_blog_202310.md":"PylQlCNr","zh_hk_docs_toyou.md":"BkHB5QKK","zh_hk_docs_pages.md":"DiJ7_Via","zh_hk_docs_join.md":"CMjvpCOu","zh_hk_docs_thanks.md":"YeAW4Q1x"}
